hmd_cli_docker/__init__.py
hmd_cli_docker/config.py
hmd_cli_docker/controller.py
hmd_cli_docker/hmd_cli_docker.py
hmd_cli_docker/utils.py
hmd_cli_docker-0.1.196.dist-info/METADATA
hmd_cli_docker-0.1.196.dist-info/WHEEL
hmd_cli_docker-0.1.196.dist-info/top_level.txt
hmd_cli_docker-0.1.196.dist-info/RECORD
